[
  {
    "题号": "1",
    "题目": "党员不能对党的纪律处分表示不服。错",
    "正确答案": "错"
  },
  {
    "题号": "2",
    "题目": "凡是写了入党申请书的人都是入党积极分子。错",
    "正确答案": "错"
  },
  {
    "题号": "3",
    "题目": "我们党的作风包括政治作风、学风、工作作风、领导作风和干部生活作风。错",
    "正确答案": "错"
  },
  {
    "题号": "4",
    "题目": "上级纪律检查委员会有权批准和改变下级纪律检查委员会对于案件所作的决定。错",
    "正确答案": "对"
  },
  {
    "题号": "5",
    "题目": "中国共产党第一部正式党章是在党的二大上通过的，同时也把誓词载入了《党章》。错",
    "正确答案": "错"
  },
  {
    "题号": "6",
    "题目": "中国共产党作为最先进的阶级——工人阶级的政党，它代表的是中国工人阶级的利益。错",
    "正确答案": "错"
  },
  {
    "题号": "7",
    "题目": "习近平新时代中国特色社会主义思想活的灵魂：解放思想、实事求是、与时俱进。错",
    "正确答案": "对"
  },
  {
    "题号": "8",
    "题目": "新时代坚持和发展中国特色社会主义的根本动力：创新。错",
    "正确答案": "错"
  },
  {
    "题号": "9",
    "题目": "勇于自我革命是我们党最鲜明的品格，也是我们党最大的优势。错",
    "正确答案": "对"
  },
  {
    "题号": "10",
    "题目": "习近平在二十大报告中提出，实现建军一百年奋斗目标，开创国防和军队现代化新局面。错",
    "正确答案": "对"
  },
  {
    "题号": "11",
    "题目": "习近平在党的二十大报告中强调，要构建高水平社会主义市场经济体制，建设现代化产业体系，全面推进乡村振兴，促进区域协调发展，推进高水平对外开放。错",
    "正确答案": "对"
  },
  {
    "题号": "12",
    "题目": "习近平在党的二十大报告中指出，坚持教育优先发展、科技自立自强、人才引领驱动，加快建设教育强国、科技强国、人才强国。错",
    "正确答案": "对"
  },
  {
    "题号": "13",
    "题目": "坚持发扬党内民主、集中全党智慧，是党中央确定的作为修改最新《党章》的一条重要原则，也是这次党章修改工作的主要特点。错",
    "正确答案": "对"
  },
  {
    "题号": "14",
    "题目": "坚持和发展中国特色社会主义的总任务是全面建成小康社会。错",
    "正确答案": "错"
  },
  {
    "题号": "15",
    "题目": "“五位一体”总体布局是指经济建设，政治建设，文化建设，社会建设，生态文明建设。错",
    "正确答案": "对"
  },
  {
    "题号": "1",
    "题目": "我们要在互相尊重主权和领土完整、互不侵犯、互不干涉内政、平等互利、和平共处五项原则的基础上，发展我国同世界各国的关系。错",
    "正确答案": "对"
  },
  {
    "题号": "2",
    "题目": "入党宣誓仪式包括：第一，宣布仪式开始，奏《国歌》；第二，党组织负责人致辞；第三，宣布参加宣誓的新党员名单；第四，宣誓。错",
    "正确答案": "错"
  },
  {
    "题号": "3",
    "题目": "国家主权统一于中华人民共和国是“一国两制”的前提。错",
    "正确答案": "对"
  },
  {
    "题号": "4",
    "题目": "党章指出，社会主义建设要实行依法治国和以德治国相结合。错",
    "正确答案": "对"
  },
  {
    "题号": "5",
    "题目": "在特殊情况下，党的中央和省、自治区、直辖市、地级市委员会可以直接接收党员。错",
    "正确答案": "错"
  },
  {
    "题号": "6",
    "题目": "我国发展新的历史方位：经过长期努力，中国特色社会主义进入了现代化。错",
    "正确答案": "错"
  },
  {
    "题号": "8",
    "题目": "新《党章》提出要发展更加广泛、更加充分、更加健全的全过程人民民主。错",
    "正确答案": "对"
  },
  {
    "题号": "9",
    "题目": "马克思主义是一成不变的理论。错",
    "正确答案": "错"
  },
  {
    "题号": "10",
    "题目": "党的最高理想和最终目标是实现共同富裕。错",
    "正确答案": "错"
  },
  {
    "题号": "11",
    "题目": "党员如果没有正当理由，连续三个月不参加党的组织生活，或不交纳党费，或不做党所分配的工作，就被认为是自行脱党。错",
    "正确答案": "错"
  },
  {
    "题号": "12",
    "题目": "2025年，我国在5G通信技术领域实现了全国领先。错",
    "正确答案": "对"
  },
  {
    "题号": "13",
    "题目": "2025年，我国某城市出台政策，鼓励企业开展“零碳工厂”建设，“零碳工厂”的核心目标是减少工厂的废弃物排放。错",
    "正确答案": "错"
  },
  {
    "题号": "14",
    "题目": "2025年，我国与周边国家加强了区域经济合作，其中与俄罗斯共同推进的跨境经济合作区建设取得显著成效。错",
    "正确答案": "对"
  },
  {
    "题号": "15",
    "题目": "2025年5月29日，我国在西昌卫星发射中心用长征三号乙运载火箭，成功将行星探测工程天问三号探测器发射升空，我国首次小行星探测与采样返回之旅正式开启。错",
    "正确答案": "错"
  },
  {
    "题号": "1",
    "题目": "党的各级领导机关，除它们派出的代表机关和在非党组织中的党组外，都由上级党委任命产生。错",
    "正确答案": "错"
  },
  {
    "题号": "2",
    "题目": "中央书记处成员由中央政治局提名，中央委员会全体会议通过。错",
    "正确答案": "错"
  },
  {
    "题号": "3",
    "题目": "预备党员的义务同正式党员一样，预备党员的权利，除了没有表决权外，也同正式党员一样。错",
    "正确答案": "错"
  },
  {
    "题号": "5",
    "题目": "实践充分证明，中国特色社会主义是当代中国发展进步的源泉，只有中国特色社会主义才能发展中国。错",
    "正确答案": "错"
  },
  {
    "题号": "6",
    "题目": "不断提高党的领导水平和执政水平、提高拒腐防变和抵御风险能力，是党巩固执政地位、实现执政使命必须解决好的重大课题。错",
    "正确答案": "对"
  },
  {
    "题号": "7",
    "题目": "开展“不忘初心、牢记使命”主题教育的根本任务是深入学习贯彻习近平新时代中国特色社会主义思想锤炼忠诚干净担当的政治品格，团结带领全国各族人民为实现伟大梦想共同奋斗。错",
    "正确答案": "对"
  },
  {
    "题号": "8",
    "题目": "新时代新征程，经济和社会发展的战略目标是，到2035年基本实现社会主义现代化，到本世纪中叶把我国建成社会主义现代化强国。错",
    "正确答案": "对"
  },
  {
    "题号": "9",
    "题目": "中国共产党第二十次全国代表大会，是在全党全国各族人民迈上全面建设社会主义现代化国家新征程、向第二个百年奋斗目标进军的关键时刻召开的一次十分重要的大会。错",
    "正确答案": "对"
  },
  {
    "题号": "10",
    "题目": "习近平在党的二十大报告中强调，必须牢固树立和践行绿水青山就是金山银山的理念，站在人与自然和谐共生的高度谋划发展。要加快发展方式绿色转型，深入推进环境污染防治，提升生态系统多样性、稳定性、持续性，积极稳妥推进碳达峰碳中和。错",
    "正确答案": "对"
  },
  {
    "题号": "11",
    "题目": "中国共产党的党旗党徽是中国共产党的象征和标志。错",
    "正确答案": "对"
  },
  {
    "题号": "12",
    "题目": "2025年，我国国内生产总值（GDP）预计将达到100万亿元。错",
    "正确答案": "错"
  },
  {
    "题号": "13",
    "题目": "2025年，某国际组织发布报告，高度评价中国在全球气候治理中的贡献，中国积极参与的全球气候治理机制是《巴黎协定》。错",
    "正确答案": "对"
  },
  {
    "题号": "14",
    "题目": "2025年6月4日，财政部，生态环境部，国家发展改革委等五部门联合发布意见，明确到2027年，长江黄河干流统一的横向生态保护补偿机制建成。错",
    "正确答案": "对"
  },
  {
    "题号": "15",
    "题目": "2025年6月10日至11日，中国网络文明大会在安徽合肥举办，本次大会以“汇聚网络正能量，引领时代新风尚”为主题。错",
    "正确答案": "对"
  },
  {
    "题号": "1",
    "题目": "中国共产党是中国工人阶级的先锋队，同时是中国公民和中华民族的先锋队。错",
    "正确答案": "错"
  },
  {
    "题号": "5",
    "题目": "共产党是工人阶级政党，是工人阶级中最普通的一部分。错",
    "正确答案": "错"
  },
  {
    "题号": "6",
    "题目": "中央委员会委员和候补委员必须有十年以上的党龄。错",
    "正确答案": "错"
  },
  {
    "题号": "8",
    "题目": "党内政治生活“四性”要求是政治性、时代性、组织性、战斗性。错",
    "正确答案": "错"
  },
  {
    "题号": "10",
    "题目": "拥有马克思主义科学理论指导是我们党鲜明的政治品格和强大的政治优势。错",
    "正确答案": "对"
  },
  {
    "题号": "12",
    "题目": "新《党章》提出坚持政治建军、改革强军、科技兴军、依法治军。错",
    "正确答案": "错"
  },
  {
    "题号": "13",
    "题目": "共享理念是持续健康发展的内在要求。错",
    "正确答案": "错"
  },
  {
    "题号": "14",
    "题目": "党的宗旨是实现共产主义。错",
    "正确答案": "错"
  },
  {
    "题号": "15",
    "题目": "2025年6月12日到15日，主题为“中非共行动，逐梦现代化”的第四届中非经贸博览会，在湖南长沙举办。错",
    "正确答案": "对"
  },
  {
    "题号": "1",
    "题目": "预备期满预备党员就是中共正式党员，开始向党组织交纳党费。错",
    "正确答案": "错"
  },
  {
    "题号": "2",
    "题目": "党的思想路线是一切相信群众，一切依靠群众，从群众中来，到群众中去。错",
    "正确答案": "错"
  },
  {
    "题号": "3",
    "题目": "中国共产党党旗为旗面缀有金黄色党徽图案的红旗。错",
    "正确答案": "对"
  },
  {
    "题号": "4",
    "题目": "成立党的新组织，必须由上级党组织决定，撤消党的原有组织，可以由该组织自行决定。错",
    "正确答案": "错"
  },
  {
    "题号": "5",
    "题目": "党的中央军事委员会组成人员由中央政治局决定。错",
    "正确答案": "错"
  },
  {
    "题号": "6",
    "题目": "《党章》规定，任何党员不论职务高低，都不能个人决定重大问题；如遇紧急情况，必须由个人作出决定时，事后要迅速向党组织报告。错",
    "正确答案": "对"
  },
  {
    "题号": "7",
    "题目": "党的任何组织和党员都必须遵守国家宪法、法律，在宪法和法律的范围内活动。错",
    "正确答案": "对"
  },
  {
    "题号": "9",
    "题目": "坚持党的工人阶级先锋队，就要排斥其他的阶级和阶层，以保持其纯洁性。错",
    "正确答案": "错"
  },
  {
    "题号": "10",
    "题目": "只有改革开放，才能发展中国、发展社会主义、发展马克思主义。错",
    "正确答案": "对"
  },
  {
    "题号": "13",
    "题目": "《复兴文库》的出版，对于我们坚定历史自信、把握时代大势、走好中国道路，以中国式现代化推进中华民族伟大复兴具有十分重要的意义。错",
    "正确答案": "对"
  },
  {
    "题号": "7",
    "题目": "党的十九大以来，以习近平同志为核心的党中央坚持把马克思列宁主义的基本原理同中国具体实际相结合、同中华优秀传统文化相结合。错",
    "正确答案": "错"
  },
  {
    "题号": "8",
    "题目": "在习近平新时代中国特色社会主义思想指导下，中国共产党领导全国各族人民，迈上全面建设社会主义现代化国家新征程、向着第一个百年奋斗目标胜利进军。错",
    "正确答案": "错"
  },
  {
    "题号": "11",
    "题目": "新时代，我国社会的主要矛盾是人民日益增长的物质文化需要同落后的社会生产之间的矛盾。错",
    "正确答案": "错"
  },
  {
    "题号": "12",
    "题目": "2025年，我国在航天领域取得重要突破，成功发射的新一代载人飞船试验船旨在为载人登月任务做准备。错",
    "正确答案": "对"
  },
  {
    "题号": "2",
    "题目": "如被讨论转正的预备党员是已延长预备期的而仍不具备党员条件的，应当取消他的预备党员资格，不能再次延长预备期。错",
    "正确答案": "对"
  },
  {
    "题号": "3",
    "题目": "党的最高理想和最终目标是社会主义社会代替资本主义社会。错",
    "正确答案": "错"
  },
  {
    "题号": "4",
    "题目": "党员根据实际情况，可以不编入党的一个支部、小组或者其他特定组织，参加党组织活动。错",
    "正确答案": "错"
  },
  {
    "题号": "6",
    "题目": "形势的发展、事业的开拓、人民的期待，都要求我们以改革创新精神全面推进党的建设新的伟大工程，全面提高党的建设科学化水平。错",
    "正确答案": "对"
  },
  {
    "题号": "7",
    "题目": "中国共产党党员永远是劳动人民的普通一员。错",
    "正确答案": "对"
  },
  {
    "题号": "10",
    "题目": "中共二十大承担着总结过去五年的工作，明确今后党和国家前进方向、奋斗目标、行动纲领，选举新一届中央领导集体的重大使命。错",
    "正确答案": "对"
  },
  {
    "题号": "11",
    "题目": "未来发展必须按照中国特色社会主义事业“五位一体”总体布局和“四个全面”战略布局，统筹推进经济建设、政治建设、文化建设、社会建设、生态文明建设，协调推进全面建成小康社会、全面深化改革、全面依法治国、全面从严治党。错",
    "正确答案": "错"
  },
  {
    "题号": "13",
    "题目": "党章规定，党员有退党的自由，但必须经过支部大会讨论后宣布除名。错",
    "正确答案": "对"
  },
  {
    "题号": "14",
    "题目": "2025年6月9日是第17个国际档案日，国家档案局举办新闻发布会发布了第六批《中国档案文献遗产名录》。错",
    "正确答案": "错"
  },
  {
    "题号": "15",
    "题目": "2025年6月15日，第17届海峡论坛大会在福建厦门举办，以续“扩大民间交流，深化融合发展”主题。错",
    "正确答案": "对"
  },
  {
    "题号": "2",
    "题目": "新时期我国工人阶级的状况发生了重大变化，但这种变化并没有改变工人阶级的先进性和历史地位。错",
    "正确答案": "对"
  },
  {
    "题号": "3",
    "题目": "在组织上入了党，思想上也就入了党。错",
    "正确答案": "错"
  },
  {
    "题号": "7",
    "题目": "习近平在二十大报告中指出，社会稳定是民族复兴的根基，国家安全是国家强盛的前提。错",
    "正确答案": "错"
  },
  {
    "题号": "9",
    "题目": "党和国家机构职能体系是中国共产党治国理政的重要保障。错",
    "正确答案": "对"
  },
  {
    "题号": "10",
    "题目": "全过程人民民主是社会主义民主政治的本质属性，是最广泛、最真实、最管用的民主。错",
    "正确答案": "对"
  },
  {
    "题号": "12",
    "题目": "全国两会指全国人民代表大会和中国人民政治协商会议。错",
    "正确答案": "对"
  },
  {
    "题号": "13",
    "题目": "2025年，我国政府强调要加强“韧性城市”建设，“韧性城市”主要是指城市能够抵御自然灾害和社会风险。错",
    "正确答案": "对"
  },
  {
    "题号": "14",
    "题目": "国防部新闻发言人张晓刚在2025年5月29日，在国防部例行记者会上介绍，“吉祥方舟”是我国自主设计建造的第二艘万吨级远洋医院船。错",
    "正确答案": "错"
  },
  {
    "题号": "2",
    "题目": "上级党组织在批准申请人入党以前，要派人同他谈话，作进一步的了解，并帮助他提高对党的认识。错",
    "正确答案": "对"
  },
  {
    "题号": "3",
    "题目": "党组织内部对重要问题发生争论，双方人数接近，一般应按多数意见执行。错",
    "正确答案": "错"
  },
  {
    "题号": "4",
    "题目": "正式组织关系未转入的党员，也可以担任所在单位的党组织负责人。错",
    "正确答案": "错"
  },
  {
    "题号": "6",
    "题目": "入党介绍人必须是正式党员。错",
    "正确答案": "对"
  },
  {
    "题号": "9",
    "题目": "社会主义民主政治的本质和核心：全心全意为人民服务。错",
    "正确答案": "错"
  },
  {
    "题号": "11",
    "题目": "中国共产党为什么能，中国特色社会主义为什么好，归根到底是马克思主义行，是中国化时代化的马克思主义行。错",
    "正确答案": "对"
  },
  {
    "题号": "13",
    "题目": "党的纪律主要包括政治纪律，组织纪律，廉洁纪律，群众纪律，工作纪律，生活纪律。错",
    "正确答案": "对"
  },
  {
    "题号": "1",
    "题目": "党支部接到申请人的入党申请后，要指定专人在一个月内同申请人谈话。错",
    "正确答案": "对"
  },
  {
    "题号": "2",
    "题目": "中国共产党第一次全国代表大会产生的中央领导机构称为中央局。错",
    "正确答案": "对"
  },
  {
    "题号": "7",
    "题目": "党的群众路线：一切为了群众，一切依靠群众，从群众中来，到群众中去，把党的正确主张变为群众的自觉行动。错",
    "正确答案": "对"
  },
  {
    "题号": "9",
    "题目": "中国特色社会主义是新时代我国发展壮大的必由之路。错",
    "正确答案": "错"
  },
  {
    "题号": "10",
    "题目": "全党必须深刻领悟“两个确立”的决定性意义，全面贯彻习近平新时代中国特色社会主义思想，把这一思想贯彻落实到党和国家工作各方面全过程。错",
    "正确答案": "对"
  },
  {
    "题号": "11",
    "题目": "社会主义初级阶段的基本路线核心是“一个中心，两个基本点”。错",
    "正确答案": "对"
  },
  {
    "题号": "12",
    "题目": "发展党员必须把政治标准放在首位，经过党的支部，坚持个别吸收的原则。错",
    "正确答案": "对"
  },
  {
    "题号": "13",
    "题目": "《中国共产党纪律处分条例》规定，党员受留党察看处分期间，没有决定权、选举权、和被选举权。错",
    "正确答案": "错"
  },
  {
    "题号": "14",
    "题目": "“四个意识”是指政治意识，大局意识，核心意识，看齐意识。错",
    "正确答案": "对"
  },
  {
    "题号": "15",
    "题目": "2025年，我国推动的“数字丝绸之路”建设，主要是为了促进数字经济领域的国际合作。错",
    "正确答案": "对"
  },
  {
    "题号": "1",
    "题目": "党员如果没有正当理由，连续一年不参加党的组织生活或不交纳党费，才被认为是自行脱党。错",
    "正确答案": "错"
  },
  {
    "题号": "3",
    "题目": "党员的党龄从预备期满转为正式党员之日算起。错",
    "正确答案": "对"
  },
  {
    "题号": "4",
    "题目": "党领导人民制定宪法和法律，又要接受人民和法律的监督与制约。错",
    "正确答案": "对"
  },
  {
    "题号": "5",
    "题目": "建设中国特色社会主义，总依据是社会主义初级阶段，总布局是五位一体，总任务是实现社会主义现代化和中华民族伟大复兴。错",
    "正确答案": "对"
  },
  {
    "题号": "6",
    "题目": "全面深化改革总目标：完善和发展中国特色社会主义制度，推进国家治理体系和治理能力现代化。错",
    "正确答案": "对"
  },
  {
    "题号": "7",
    "题目": "新时代“三农”工作总抓手：实施乡村振兴战略。错",
    "正确答案": "对"
  },
  {
    "题号": "14",
    "题目": "2025年，我国提出的“绿色发展新举措”中重点强调了天然气在能源结构中的地位。错",
    "正确答案": "错"
  },
  {
    "题号": "3",
    "题目": "在党组织讨论决定对党员的党纪处分或作出鉴定时，本人无权参加和进行申辩。错",
    "正确答案": "错"
  },
  {
    "题号": "8",
    "题目": "二十大修订的新《党章》首次提出要坚持创新、协调、绿色、开放、共享的发展理念。错",
    "正确答案": "错"
  },
  {
    "题号": "11",
    "题目": "改革是党执政兴国的第一要务。错",
    "正确答案": "错"
  },
  {
    "题号": "14",
    "题目": "2025年6月13日上午，中共中央在人民大会堂举行座谈会纪念陈云同志诞生120周年。错",
    "正确答案": "对"
  },
  {
    "题号": "4",
    "题目": "党的最高领导机关，是党的全国代表大会和它所产生的中央政治局。错",
    "正确答案": "错"
  },
  {
    "题号": "12",
    "题目": "党的十八大以来，我国坚持全面深化改革，充分发挥经济体制改革的牵引作用，不断完善社会主义市场经济体制，以经济高质量发展推动各项事业高质量发展。错",
    "正确答案": "对"
  },
  {
    "题号": "15",
    "题目": "2025年6月9日起，中方对沙特，阿曼，科威特，巴林持普通护照人员实行免签政策。至此，适用单方面免签政策来华国家已扩展至47个。错",
    "正确答案": "对"
  },
  {
    "题号": "2",
    "题目": "年满十八岁的中国工人、农民、军人、知识分子和其他革命分子，满足条件的，可以申请加入中国共产党。错",
    "正确答案": "错"
  },
  {
    "题号": "3",
    "题目": "党的思想路线是一切从实际出发，理论联系实际，在实践中检验真理和发展真理。错",
    "正确答案": "错"
  },
  {
    "题号": "6",
    "题目": "推进经济结构战略性调整，这是加快转变经济发展方式的主攻方向。错",
    "正确答案": "对"
  },
  {
    "题号": "12",
    "题目": "“九五共识”是确保两岸关系和平发展的关键。错",
    "正确答案": "错"
  },
  {
    "题号": "2",
    "题目": "申请人一经被发展为预备党员，就要按期交纳党费，就有表决权、选举权和被选举权。错",
    "正确答案": "错"
  },
  {
    "题号": "11",
    "题目": "教育、科技、创新是全面建设社会主义现代化国家的基础性、战略性支撑。错",
    "正确答案": "错"
  },
  {
    "题号": "2",
    "题目": "党的基层委员会、总支部委员会、支部委员会每届任期两年或三年。错",
    "正确答案": "错"
  },
  {
    "题号": "7",
    "题目": "马克思主义永葆生机活力的奥妙在于始终与时代同步伐、与人民共命运，在关注和解答时代和实践提出的重大课题中作出新概括、获得新认识、形成新成果。错",
    "正确答案": "对"
  },
  {
    "题号": "11",
    "题目": "“两个维护”是指坚决维护习近平总书记党中央的核心，全党党的核心地位，坚决维护党中央权威和集中统一领导。错",
    "正确答案": "对"
  },
  {
    "题号": "14",
    "题目": "我们党最鲜明的品格是勇于自我革命，实事求是。错",
    "正确答案": "错"
  },
  {
    "题号": "6",
    "题目": "党组织必须设书记、副书记。错",
    "正确答案": "错"
  },
  {
    "题号": "7",
    "题目": "发展党员必须坚持入党自愿原则。错",
    "正确答案": "对"
  },
  {
    "题号": "11",
    "题目": "预备党员的预备期为两年期间没有表决权选举权和被选举权。错",
    "正确答案": "错"
  },
  {
    "题号": "13",
    "题目": "2025年，我国成功发射了天宫T字基本型空间站航天器，标志着我国在空间站建设方面取得重要进展。错",
    "正确答案": "对"
  },
  {
    "题号": "4",
    "题目": "临时党支部是可以发展党员的。错",
    "正确答案": "错"
  },
  {
    "题号": "5",
    "题目": "党的地方各级委员会全体会议，每年至少召开两次。错",
    "正确答案": "对"
  },
  {
    "题号": "14",
    "题目": "党的根本纲领性文件是《中华人民共和国宪法》。错",
    "正确答案": "错"
  },
  {
    "题号": "2",
    "题目": "召开接收新党员的支部大会进行表决时，到会的人员都要举手表决是否同意申请人加入党组织。错",
    "正确答案": "错"
  },
  {
    "题号": "5",
    "题目": "我们党的最大政治优势是密切联系群众，党执政后的最大危险是脱离群众。错",
    "正确答案": "对"
  },
  {
    "题号": "8",
    "题目": "党员领导干部不重视家风建设，对配偶、子女及其配偶失管失教，造成不良影响或者严重后果的，给予警告或者严重警告处分；情节严重的，给予撤销党内职务处分。错",
    "正确答案": "对"
  },
  {
    "题号": "9",
    "题目": "加强中央和国家机关党的建设的首要任务：带头做到“两个维护”。错",
    "正确答案": "对"
  },
  {
    "题号": "13",
    "题目": "全面从严治党，基础在全面，关键在严，要害在治。错",
    "正确答案": "对"
  },
  {
    "题号": "5",
    "题目": "中国共产党领导人民发展社会主义民主政治。要发展更加广泛、更加充分、更加健全的社会主义法制，切实保障人民管理国家事务和社会事务、管理经济和文化事业的权利。错",
    "正确答案": "错"
  },
  {
    "题号": "10",
    "题目": "十八大报告指出，我国社会的主要矛盾已经转化为人民日益增长的美好生活需要和不平衡不充分的发展之间的矛盾。错",
    "正确答案": "错"
  },
  {
    "题号": "1",
    "题目": "没有特殊理由，党员不能自由退党。错",
    "正确答案": "错"
  },
  {
    "题号": "7",
    "题目": "实现中华民族伟大复兴是近代以来中华民族最伟大的梦想。伟大斗争，伟大工程，伟大事业，伟大梦想，紧密联系、相互贯通、相互作用，其中起决定性作用的是党的建设新的伟大工程。错",
    "正确答案": "对"
  },
  {
    "题号": "8",
    "题目": "全面推进依法治国总目标：建设中国特色社会主义法治体系，建设社会主义法治国家。错",
    "正确答案": "对"
  },
  {
    "题号": "1",
    "题目": "没有中国国籍的外国人不能加入中国共产党。错",
    "正确答案": "对"
  },
  {
    "题号": "10",
    "题目": "中国共产党人深刻认识到，只有把马克思主义基本原理同中国具体实际相结合、同中华传统文化相结合，坚持运用辩证唯物主义和历史唯物主义，才能正确回答时代和实践提出的重大问题，才能始终保持马克思主义的蓬勃生机和旺盛活力。错",
    "正确答案": "错"
  },
  {
    "题号": "3",
    "题目": "当今世界，霸权主义和强权政治已经消亡，局部冲突和热点问题逐渐缓解，全球经济日渐平衡，南北差距越来越小，世界和平与发展呈现出大好局面。错",
    "正确答案": "错"
  },
  {
    "题号": "2",
    "题目": "党风问题、党同人民群众联系问题是关系党生死存亡的问题。错",
    "正确答案": "对"
  },
  {
    "题号": "3",
    "题目": "中央军事委员会的政治工作机关是中国人民解放军总政治部，它负责管理军队中党的工作和政治工作。错",
    "正确答案": "对"
  },
  {
    "题号": "4",
    "题目": "企业、农村、机关、学校、科研院所、街道社区、社会团体、社会中介组织、人民解放军连队和其他基层单位，凡是有正式党员3人以上的，都必须成立党的基层组织。错",
    "正确答案": "对"
  },
  {
    "题号": "13",
    "题目": "近年来，我国着力提升儿科服务供给，全国8000多所综合医院能够开展儿科门诊或住院服务，超过80%的基层医疗卫生机构能够提供儿童常见病诊疗服务。错",
    "正确答案": "对"
  },
  {
    "题号": "15",
    "题目": "2025年6月6日，我国在太原卫星发射中心使用长征六号改运载火箭，成功将卫星互联网低轨04组卫星发射升空，卫星顺利进入预定轨道，发射任务获得圆满成功。错",
    "正确答案": "对"
  },
  {
    "题号": "5",
    "题目": "预备党员的权利，除了没有选举权和被选举权以外，同正式党员一样。错",
    "正确答案": "错"
  },
  {
    "题号": "6",
    "题目": "党纪处分有警告、严重警告、记过、留党察看、开除党籍五种。错",
    "正确答案": "错"
  },
  {
    "题号": "7",
    "题目": "为人民服务是党的根本宗旨，执政为民是检验党一切执政活动的最高标准。错",
    "正确答案": "错"
  },
  {
    "题号": "6",
    "题目": "习近平新时代中国特色社会主义思想的核心要义：坚持和发展中国特色社会主义。错",
    "正确答案": "对"
  },
  {
    "题号": "7",
    "题目": "改革是引领发展的第一动力。错",
    "正确答案": "错"
  },
  {
    "题号": "10",
    "题目": "科学技术是历史发展的根本动力。错",
    "正确答案": "错"
  }
]